{
    "demographics":
    {
        "age_group_distribution":
        {
            "0-9":
            {
                "index":
                {
                    "this": 100.0, "country": 105.0
                },
                "name": "0-9",
                "error_ratio":
                {
                    "this": null, "country": null
                },
                "values": {
                    "this": 21.39, "country": 20.29
                },
                "numerators": {
                    "this": 864331.0, "country": 10505203.0
                },
                "error": {
                    "this": 0, "country": 0
                },
                "numerator_errors": {
                    "this": 0, "country": 0
                }
            },
            "10-19": {"index": {"this": 100.0, "country": 110.0}, "name": "10-19", "error_ratio": {"this": null, "country": null}, "values": {"this": 20.31, "country": 18.54}, "numerators": {"this": 820626.0, "country": 9598363.0}, "error": {"this": 0, "country": 0}, "numerator_errors": {"this": 0, "country": 0}
      },
            "20-29": {"index": {"this": 100.0, "country": 101.0}, "name": "20-29", "error_ratio": {"this": null, "country": null}, "values": {"this": 20.31, "country": 20.15}, "numerators": {"this": 820637.0, "country": 10433859.0}, "error": {"this": 0, "country": 0}, "numerator_errors": {"this": 0, "country": 0}},
            "30-39": {"index": {"this": 100.0, "country": 95.0}, "name": "30-39", "error_ratio": {"this": null, "country": null}, "values": {"this": 13.7, "country": 14.48}, "numerators": {"this": 553471.0, "country": 7496777.0}, "error": {"this": 0, "country": 0}, "numerator_errors": {"this": 0, "country": 0}},
            "40-49": {"index": {"this": 100.0, "country": 95.0}, "name": "40-49", "error_ratio": {"this": null, "country": null}, "values": {"this": 10.17, "country": 10.76}, "numerators": {"this": 410678.0, "country": 5568901.0}, "error": {"this": 0, "country": 0}, "numerator_errors": {"this": 0, "country": 0}},
            "50-59": {"index": {"this": 100.0, "country": 91.0}, "name": "50-59", "error_ratio": {"this": null, "country": null}, "values": {"this": 7.08, "country": 7.76}, "numerators": {"this": 286042.0, "country": 4015697.0}, "error": {"this": 0, "country": 0}, "numerator_errors": {"this": 0, "country": 0}},
            "60-69": {"index": {"this": 100.0, "country": 87.0}, "name": "60-69", "error_ratio": {"this": null, "country": null}, "values": {"this": 3.93, "country": 4.53}, "numerators": {"this": 158658.0, "country": 2343573.0}, "error": {"this": 0, "country": 0}, "numerator_errors": {"this": 0, "country": 0}},
            "70-79": {"index": {"this": 100.0, "country": 86.0}, "name": "70-79", "error_ratio": {"this": null, "country": null}, "values": {"this": 2.05, "country": 2.38}, "numerators": {"this": 82978.0, "country": 1229598.0}, "error": {"this": 0, "country": 0}, "numerator_errors": {"this": 0, "country": 0}},
            "80+": {"index": {"this": 100.0, "country": 94.0}, "name": "80+", "error_ratio": {"this": null, "country": null}, "values": {"this": 1.05, "country": 1.12}, "numerators": {"this": 42520.0, "country": 578589.0}, "error": {"this": 0, "country": 0}, "numerator_errors": {"this": 0, "country": 0}},
            "metadata": {"table_id": "AGEGROUPSIN5YEARS"}}, "sex_ratio": {"Female": {"index": {"this": 100.0, "country": 100.0}, "name": "Female", "error_ratio": {"this": null, "country": null}, "values": {"this": 51.14, "country": 51.35}, "numerators": {"this": 1974055, "country": 25188791}, "error": {"this": 0, "country": 0}, "numerator_errors": {"this": 0, "country": 0}}, "Male": {"index": {"this": 100.0, "country": 100.0}, "name": "Male", "error_ratio": {"this": null, "country": null}, "values": {"this": 48.86, "country": 48.65}, "numerators": {"this": 2065884.0, "country": 26581770.0}, "error": {"this": 0, "country": 0}, "numerator_errors": {"this": 0, "country": 0}}, "metadata": {"table_id": "GENDER"}}, "median_age": {"index": {"this": 100.0, "country": 92.0}, "name": "Median age", "error_ratio": {"this": null, "country": null}, "values": {"this": 23.0, "country": 25.0}, "numerators": {"this": 0, "province": 0, "country": 0}, "error": {"this": 0, "country": 0}, "numerator_errors": {"this": 0, "province": 0, "country": 0}}, "age_category_distribution": {"under_18": {"index": {"this": 100.0, "country": 107.0}, "name": "Under 18", "error_ratio": {"this": null, "country": null}, "values": {"this": 37.51, "country": 34.9}, "numerators": {"this": 0, "province": 0, "country": 0}, "error": {"this": 0, "country": 0}, "numerator_errors": {"this": 0, "province": 0, "country": 0}}, "18_to_64": {"index": {"this": 100.0, "country": 97.0}, "name": "18 to 64", "error_ratio": {"this": null, "country": null}, "values": {"this": 57.79, "country": 59.76}, "numerators": {"this": 0, "province": 0, "country": 0}, "error": {"this": 0, "country": 0}, "numerator_errors": {"this": 0, "province": 0, "country": 0}}, "65_and_over": {"index": {"this": 100.0, "country": 88.0}, "name": "65 and over", "error_ratio": {"this": null, "country": null}, "values": {"this": 4.7, "country": 5.34}, "numerators": {"this": 0, "province": 0, "country": 0}, "error": {"this": 0, "country": 0}, "numerator_errors": {"this": 0, "province": 0, "country": 0}}, "metadata": {"table_id": "AGEINCOMPLETEDYEARS"}}, "total_population": {"index": {"this": 100.0, "country": 8.0}, "name": "People", "error_ratio": {"this": null, "country": null}, "values": {"this": 4039939.0, "country": 51770561.0}, "numerators": {"this": 0, "province": 0, "country": 0}, "error": {"this": 0, "country": 0}, "numerator_errors": {"this": 0, "province": 0, "country": 0}}, "population_group_distribution": {"Black African": {"index": {"this": 100.0, "country": 114.0}, "name": "Black African", "error_ratio": {"this": null, "country": null}, "values": {"this": 90.65, "country": 79.2}, "numerators": {"this": 3662219, "country": 41000938}, "error": {"this": 0, "country": 0}, "numerator_errors": {"this": 0, "country": 0}}, "Coloured": {"index": {"this": 100.0, "country": 10.0}, "name": "Coloured", "error_ratio": {"this": null, "country": null}, "values": {"this": 0.91, "country": 8.92}, "numerators": {"this": 36611, "country": 4615401}, "error": {"this": 0, "country": 0}, "numerator_errors": {"this": 0, "country": 0}}, "Indian or Asian": {"index": {"this": 100.0, "country": 28.0}, "name": "Indian or Asian", "error_ratio": {"this": null, "country": null}, "values": {"this": 0.69, "country": 2.49}, "numerators": {"this": 27917, "country": 1286930}, "error": {"this": 0, "country": 0}, "numerator_errors": {"this": 0, "country": 0}}, "Other": {"index": {"this": 100.0, "country": 44.0}, "name": "Other", "error_ratio": {"this": null, "country": null}, "values": {"this": 0.24, "country": 0.54}, "numerators": {"this": 9597, "country": 280454}, "error": {"this": 0, "country": 0}, "numerator_errors": {"this": 0, "country": 0}}, "White": {"index": {"this": 100.0, "country": 85.0}, "name": "White", "error_ratio": {"this": null, "country": null}, "values": {"this": 7.51, "country": 8.86}, "numerators": {"this": 303595, "country": 4586838}, "error": {"this": 0, "country": 0}, "numerator_errors": {"this": 0, "country": 0}}, "metadata": {"table_id": "POPULATIONGROUP"}}}, "economics": {"individual_income_distribution": {"R0": {"index": {"this": 100.0, "country": 101.0}, "name": "R0", "error_ratio": {"this": null, "country": null}, "values": {"this": 8.69, "country": 8.59}, "numerators": {"this": 84296.0, "country": 1132167.0}, "error": {"this": 0, "country": 0}, "numerator_errors": {"this": 0, "country": 0}}, "Under R400": {"index": {"this": 100.0, "country": 105.0}, "name": "Under R400", "error_ratio": {"this": null, "country": null}, "values": {"this": 3.34, "country": 3.18}, "numerators": {"this": 32356.0, "country": 419334.0}, "error": {"this": 0, "country": 0}, "numerator_errors": {"this": 0, "country": 0}}, "R400 - R800": {"index": {"this": 100.0, "country": 114.0}, "name": "R400 - R800", "error_ratio": {"this": null, "country": null}, "values": {"this": 6.87, "country": 6.04}, "numerators": {"this": 66668.0, "country": 796136.0}, "error": {"this": 0, "country": 0}, "numerator_errors": {"this": 0, "country": 0}}, "R800 - R2k": {"index": {"this": 100.0, "country": 116.0}, "name": "R800 - R2k", "error_ratio": {"this": null, "country": null}, "values": {"this": 19.42, "country": 16.75}, "numerators": {"this": 188320.0, "country": 2208054.0}, "error": {"this": 0, "country": 0}, "numerator_errors": {"this": 0, "country": 0}}, "R2k - R3k": {"index": {"this": 100.0, "country": 103.0}, "name": "R2k - R3k", "error_ratio": {"this": null, "country": null}, "values": {"this": 19.34, "country": 18.74}, "numerators": {"this": 187543.0, "country": 2469585.0}, "error": {"this": 0, "country": 0}, "numerator_errors": {"this": 0, "country": 0}}, "R3k - R6k": {"index": {"this": 100.0, "country": 98.0}, "name": "R3k - R6k", "error_ratio": {"this": null, "country": null}, "values": {"this": 14.39, "country": 14.73}, "numerators": {"this": 139531.0, "country": 1940963.0}, "error": {"this": 0, "country": 0}, "numerator_errors": {"this": 0, "country": 0}}, "R6k - R13k": {"index": {"this": 100.0, "country": 95.0}, "name": "R6k - R13k", "error_ratio": {"this": null, "country": null}, "values": {"this": 11.87, "country": 12.52}, "numerators": {"this": 115111.0, "country": 1649796.0}, "error": {"this": 0, "country": 0}, "numerator_errors": {"this": 0, "country": 0}}, "R13k - R26k": {"index": {"this": 100.0, "country": 89.0}, "name": "R13k - R26k", "error_ratio": {"this": null, "country": null}, "values": {"this": 8.09, "country": 9.13}, "numerators": {"this": 78419.0, "country": 1203627.0}, "error": {"this": 0, "country": 0}, "numerator_errors": {"this": 0, "country": 0}}, "R26k - R51k": {"index": {"this": 100.0, "country": 78.0}, "name": "R26k - R51k", "error_ratio": {"this": null, "country": null}, "values": {"this": 2.93, "country": 3.75}, "numerators": {"this": 28387.0, "country": 494584.0}, "error": {"this": 0, "country": 0}, "numerator_errors": {"this": 0, "country": 0}}, "R51k - R102k": {"index": {"this": 100.0, "country": 62.0}, "name": "R51k - R102k", "error_ratio": {"this": null, "country": null}, "values": {"this": 0.73, "country": 1.18}, "numerators": {"this": 7059.0, "country": 155154.0}, "error": {"this": 0, "country": 0}, "numerator_errors": {"this": 0, "country": 0}}, "Over R102k": {"index": {"this": 100.0, "country": 68.0}, "name": "Over R102k", "error_ratio": {"this": null, "country": null}, "values": {"this": 0.45, "country": 0.66}, "numerators": {"this": 4370.0, "country": 87467.0}, "error": {"this": 0, "country": 0}, "numerator_errors": {"this": 0, "country": 0}}, "Unspecified": {"index": {"this": 100.0, "country": 82.0}, "name": "Unspecified", "error_ratio": {"this": null, "country": null}, "values": {"this": 3.89, "country": 4.73}, "numerators": {"this": 37712.0, "country": 623210.0}, "error": {"this": 0, "country": 0}, "numerator_errors": {"this": 0, "country": 0}}, "metadata": {"universe": "Officially employed individuals", "table_id": "INDIVIDUALMONTHLYINCOME"}}, "employment_status": {"Employed": {"index": {"this": 100.0, "country": 96.0}, "name": "Employed", "error_ratio": {"this": null, "country": null}, "values": {"this": 37.45, "country": 38.87}, "numerators": {"this": 969771, "country": 13180077}, "error": {"this": 0, "country": 0}, "numerator_errors": {"this": 0, "country": 0}}, "Unemployed": {"index": {"this": 100.0, "country": 105.0}, "name": "Unemployed", "error_ratio": {"this": null, "country": null}, "values": {"this": 17.31, "country": 16.5}, "numerators": {"this": 448126, "country": 5594055}, "error": {"this": 0, "country": 0}, "numerator_errors": {"this": 0, "country": 0}}, "metadata": {"universe": "Workers 15 and over", "table_id": "OFFICIALEMPLOYMENTSTATUS"}, "Discouraged work-seeker": {"index": {"this": 100.0, "country": 108.0}, "name": "Discouraged work-seeker", "error_ratio": {"this": null, "country": null}, "values": {"this": 5.83, "country": 5.41}, "numerators": {"this": 150844, "country": 1835092}, "error": {"this": 0, "country": 0}, "numerator_errors": {"this": 0, "country": 0}}, "Other not economically active": {"index": {"this": 100.0, "country": 101.0}, "name": "Other not economically active", "error_ratio": {"this": null, "country": null}, "values": {"this": 39.42, "country": 39.21}, "numerators": {"this": 1020806, "country": 13295256}, "error": {"this": 0, "country": 0}, "numerator_errors": {"this": 0, "country": 0}}}, "sector_type_distribution": {"Do not know": {"index": {"this": 100.0, "country": 105.0}, "name": "Do not know", "error_ratio": {"this": null, "country": null}, "values": {"this": 2.48, "country": 2.37}, "numerators": {"this": 24499, "country": 318446}, "error": {"this": 0, "country": 0}, "numerator_errors": {"this": 0, "country": 0}}, "In the formal sector": {"index": {"this": 100.0, "country": 93.0}, "name": "In the formal sector", "error_ratio": {"this": null, "country": null}, "values": {"this": 68.78, "country": 74.02}, "numerators": {"this": 678945, "country": 9956436}, "error": {"this": 0, "country": 0}, "numerator_errors": {"this": 0, "country": 0}}, "In the informal sector": {"index": {"this": 100.0, "country": 135.0}, "name": "In the informal sector", "error_ratio": {"this": null, "country": null}, "values": {"this": 16.52, "country": 12.2}, "numerators": {"this": 163124, "country": 1640901}, "error": {"this": 0, "country": 0}, "numerator_errors": {"this": 0, "country": 0}}, "Private household": {"index": {"this": 100.0, "country": 107.0}, "name": "Private household", "error_ratio": {"this": null, "country": null}, "values": {"this": 12.22, "country": 11.41}, "numerators": {"this": 120594, "country": 1534843}, "error": {"this": 0, "country": 0}, "numerator_errors": {"this": 0, "country": 0}}, "metadata": {"table_id": "TYPEOFSECTOR"}}}, "service_delivery": {"electricity_access_distribution": {"total_no_elec": {"index": {"this": 100.0, "country": 89.0}, "name": "No electricity", "error_ratio": {"this": null, "country": null}, "values": {"this": 13.0, "country": 14.68}, "numerators": {"this": 139811.0, "country": 2120974.0}, "error": {"this": 0, "country": 0}, "numerator_errors": {"this": 0, "country": 0}}, "total_some_not_all_elec": {"index": {"this": 100.0, "country": 114.0}, "name": "Have electricity for some things", "error_ratio": {"this": null, "country": null}, "values": {"this": 33.51, "country": 29.38}, "numerators": {"this": 360362.0, "country": 4246047.0}, "error": {"this": 0, "country": 0}, "numerator_errors": {"this": 0, "country": 0}}, "total_all_elec": {"index": {"this": 100.0, "country": 96.0}, "name": "Have electricity for everything", "error_ratio": {"this": null, "country": null}, "values": {"this": 53.49, "country": 55.94}, "numerators": {"this": 575315.0, "country": 8083139.0}, "error": {"this": 0, "country": 0}, "numerator_errors": {"this": 0, "country": 0}}, "metadata": {"table_id": "ELECTRICITYAVAILABILITY"}}, "refuse_disposal_distribution": {"Own dump": {"index": {"this": 100.0, "country": 151.0}, "name": "Own dump", "error_ratio": {"this": null, "country": null}, "values": {"this": 47.36, "country": 31.38}, "numerators": {"this": 1913183, "country": 16247036}, "error": {"this": 0, "country": 0}, "numerator_errors": {"this": 0, "country": 0}}, "Service provider (regularly)": {"index": {"this": 100.0, "country": 69.0}, "name": "Service provider (regularly)", "error_ratio": {"this": null, "country": null}, "values": {"this": 39.91, "country": 57.97}, "numerators": {"this": 1612426, "country": 30013366}, "error": {"this": 0, "country": 0}, "numerator_errors": {"this": 0, "country": 0}}, "None": {"index": {"this": 100.0, "country": 135.0}, "name": "None", "error_ratio": {"this": null, "country": null}, "values": {"this": 8.08, "country": 5.97}, "numerators": {"this": 326442, "country": 3090002}, "error": {"this": 0, "country": 0}, "numerator_errors": {"this": 0, "country": 0}}, "metadata": {"table_id": "REFUSEDISPOSAL"}, "Other": {"index": {"this": 100.0, "country": 100.0}, "numerator_errors": {"this": 0.0}, "error_ratio": {"this": null}, "values": {"this": 4.65, "country": 4.67}, "numerators": {"this": 187888.0, "country": 2420158.0}, "error": {"this": 0.0}, "name": "Other"}}, "percentage_water_from_service_provider": {"index": {"this": 100.0, "country": 96.0}, "name": "Are getting water from a regional or local service provider", "error_ratio": {"this": null, "country": null}, "values": {"this": 73.58, "country": 76.89}, "numerators": {"this": 2972539.0, "country": 39807757.0}, "error": {"this": 0, "country": 0}, "numerator_errors": {"this": 0, "country": 0}}, "water_source_distribution": {"Service provider": {"index": {"this": 100.0, "country": 96.0}, "name": "Service provider", "error_ratio": {"this": null, "country": null}, "values": {"this": 73.58, "country": 76.89}, "numerators": {"this": 2972539, "country": 39807757}, "error": {"this": 0, "country": 0}, "numerator_errors": {"this": 0, "country": 0}}, "Borehole": {"index": {"this": 100.0, "country": 129.0}, "name": "Borehole", "error_ratio": {"this": null, "country": null}, "values": {"this": 8.05, "country": 6.24}, "numerators": {"this": 325208, "country": 3229413}, "error": {"this": 0, "country": 0}, "numerator_errors": {"this": 0, "country": 0}}, "Tanker": {"index": {"this": 100.0, "country": 191.0}, "name": "Tanker", "error_ratio": {"this": null, "country": null}, "values": {"this": 5.11, "country": 2.67}, "numerators": {"this": 206386, "country": 1382835}, "error": {"this": 0, "country": 0}, "numerator_errors": {"this": 0, "country": 0}}, "metadata": {"table_id": "SOURCEOFWATER"}, "Other": {"index": {"this": 100.0, "country": 93.0}, "numerator_errors": {"this": 0.0}, "error_ratio": {"this": null}, "values": {"this": 13.26, "country": 14.2}, "numerators": {"this": 535806.0, "country": 7350555.0}, "error": {"this": 0.0}, "name": "Other"}}, "percentage_electricity_access": {"index": {"this": 100.0, "country": 102.0}, "name": "Have electricity for at least one of cooking, heating or lighting", "error_ratio": {"this": null, "country": null}, "values": {"this": 87.0, "country": 85.32}, "numerators": {"this": 935677.0, "country": 12329186.0}, "error": {"this": 0, "country": 0}, "numerator_errors": {"this": 0, "country": 0}}, "percentage_ref_disp_from_service_provider": {"index": {"this": 100.0, "country": 69.0}, "name": "Are getting refuse disposal from a local authority or private company", "error_ratio": {"this": null, "country": null}, "values": {"this": 41.0, "country": 59.4}, "numerators": {"this": 1656425.0, "country": 30752725.0}, "error": {"this": 0, "country": 0}, "numerator_errors": {"this": 0, "country": 0}}}, "elections": {"municipal_2011": {"registered_voters": {"index": {"this": 100.0, "country": 7.0}, "name": "Number of registered voters", "error_ratio": {"this": null, "country": null}, "values": {"this": 1718309, "country": 23654347}, "numerators": {"this": 0, "province": 0, "country": 0}, "error": {"this": 0, "country": 0}, "numerator_errors": {"this": 0, "province": 0, "country": 0}}, "average_turnout": {"index": {"this": 100.0, "country": 97.0}, "name": "Of registered voters cast their vote", "error_ratio": {"this": null, "country": null}, "values": {"this": 56.18, "country": 58.05}, "numerators": {"this": 961235, "country": 13647511}, "error": {"this": 0, "country": 0}, "numerator_errors": {"this": 0, "country": 0}}, "name": "municipal 2011", "party_distribution": {"ANC": {"index": {"this": 100.0, "country": 126.0}, "numerator_errors": {"this": 0, "country": 0}, "name": "ANC", "error_ratio": {"this": null, "country": null}, "values": {"this": 79.19, "country": 62.93}, "numerators": {"this": 744729, "country": 8405429}, "error": {"this": 0, "country": 0}, "name_long": "AFRICAN NATIONAL CONGRESS"}, "DA": {"index": {"this": 100.0, "country": 57.0}, "numerator_errors": {"this": 0, "country": 0}, "name": "DA", "error_ratio": {"this": null, "country": null}, "values": {"this": 13.68, "country": 24.08}, "numerators": {"this": 128617, "country": 3216006}, "error": {"this": 0, "country": 0}, "name_long": "DEMOCRATIC ALLIANCE/DEMOKRATIESE ALLIANSIE"}, "BRA": {"index": {"this": 100.0, "country": 1487.0}, "numerator_errors": {"this": 0, "country": 0}, "name": "BRA", "error_ratio": {"this": null, "country": null}, "values": {"this": 1.19, "country": 0.08}, "numerators": {"this": 11153, "country": 11153}, "error": {"this": 0, "country": 0}, "name_long": "BUSHBUCKRIDGE RESIDENTS ASSOCIATION"}, "CTP": {"index": {"this": 100.0, "country": 50.0}, "numerator_errors": {"this": 0, "country": 0}, "name": "CTP", "error_ratio": {"this": null, "country": null}, "values": {"this": 1.11, "country": 2.22}, "numerators": {"this": 10475, "country": 296624}, "error": {"this": 0, "country": 0}, "name_long": "CONGRESS  OF THE PEOPLE"}, "APC": {"index": {"this": 100.0, "country": 217.0}, "numerator_errors": {"this": 0, "country": 0}, "name": "APC", "error_ratio": {"this": null, "country": null}, "values": {"this": 0.89, "country": 0.41}, "numerators": {"this": 8339, "country": 54332}, "error": {"this": 0, "country": 0}, "name_long": "AFRICAN PEOPLE'S CONVENTION"}, "PACA": {"index": {"this": 100.0, "country": 161.0}, "numerator_errors": {"this": 0, "country": 0}, "name": "PACA", "error_ratio": {"this": null, "country": null}, "values": {"this": 0.66, "country": 0.41}, "numerators": {"this": 6211, "country": 54846}, "error": {"this": 0, "country": 0}, "name_long": "PAN AFRICANIST CONGRESS OF AZANIA"}, "NFP": {"index": {"this": 100.0, "country": 26.0}, "numerator_errors": {"this": 0, "country": 0}, "name": "NFP", "error_ratio": {"this": null, "country": null}, "values": {"this": 0.63, "country": 2.38}, "numerators": {"this": 5897, "country": 318352}, "error": {"this": 0, "country": 0}, "name_long": "NATIONAL FREEDOM PARTY"}, "SPP": {"index": {"this": 100.0, "country": 1525.0}, "numerator_errors": {"this": 0, "country": 0}, "name": "SPP", "error_ratio": {"this": null, "country": null}, "values": {"this": 0.61, "country": 0.04}, "numerators": {"this": 5712, "country": 5712}, "error": {"this": 0, "country": 0}, "name_long": "SINDAWONYE PROGRESSIVE PARTY"}, "Other": {"index": {"this": 100.0}, "numerator_errors": {"this": 0}, "name": "Other", "error_ratio": {"this": null}, "values": {"this": 2.05}, "numerators": {"this": 19289.0}, "error": {"this": 0}, "name_long": "Other"}, "metadata": {"universe": "Proportional representative (PR) ballots only", "table_id": "VOTESUMMARY"}}}}, "education": {"educational_attainment": {"percent_fet_or_higher": {"index": {"this": 100.0, "country": 94.0}, "name": "Completed Matric or higher", "error_ratio": {"this": null, "country": null}, "values": {"this": 35.32, "country": 37.7}, "numerators": {"this": 680814.0, "country": 9912490.0}, "error": {"this": 0, "country": 0}, "numerator_errors": {"this": 0, "country": 0}}, "percent_get_or_higher": {"index": {"this": 100.0, "country": 93.0}, "name": "Completed Grade 9 or higher", "error_ratio": {"this": null, "country": null}, "values": {"this": 57.94, "country": 62.16}, "numerators": {"this": 1116735.0, "country": 16342647.0}, "error": {"this": 0, "country": 0}, "numerator_errors": {"this": 0, "country": 0}}, "metadata": {"universe": "Invididuals 25 and over"}}, "educational_attainment_distribution": {"None": {"index": {"this": 100.0, "country": 167.0}, "name": "None", "error_ratio": {"this": null, "country": null}, "values": {"this": 16.32, "country": 9.75}, "numerators": {"this": 314519.0, "country": 2564210.0}, "error": {"this": 0, "country": 0}, "numerator_errors": {"this": 0, "country": 0}}, "Other": {"index": {"this": 100.0, "country": 79.0}, "name": "Other", "error_ratio": {"this": null, "country": null}, "values": {"this": 1.73, "country": 2.2}, "numerators": {"this": 33410.0, "country": 578127.0}, "error": {"this": 0, "country": 0}, "numerator_errors": {"this": 0, "country": 0}}, "Some primary": {"index": {"this": 100.0, "country": 97.0}, "name": "Some primary", "error_ratio": {"this": null, "country": null}, "values": {"this": 13.22, "country": 13.58}, "numerators": {"this": 254885.0, "country": 3570075.0}, "error": {"this": 0, "country": 0}, "numerator_errors": {"this": 0, "country": 0}}, "Primary": {"index": {"this": 100.0, "country": 88.0}, "name": "Primary", "error_ratio": {"this": null, "country": null}, "values": {"this": 10.79, "country": 12.31}, "numerators": {"this": 207893.0, "country": 3237394.0}, "error": {"this": 0, "country": 0}, "numerator_errors": {"this": 0, "country": 0}}, "Grade 9": {"index": {"this": 100.0, "country": 84.0}, "name": "Grade 9", "error_ratio": {"this": null, "country": null}, "values": {"this": 4.62, "country": 5.5}, "numerators": {"this": 89000.0, "country": 1446046.0}, "error": {"this": 0, "country": 0}, "numerator_errors": {"this": 0, "country": 0}}, "Some secondary": {"index": {"this": 100.0, "country": 95.0}, "name": "Some secondary", "error_ratio": {"this": null, "country": null}, "values": {"this": 18.0, "country": 18.96}, "numerators": {"this": 346921.0, "country": 4984111.0}, "error": {"this": 0, "country": 0}, "numerator_errors": {"this": 0, "country": 0}}, "Grade 12 (Matric)": {"index": {"this": 100.0, "country": 101.0}, "name": "Grade 12 (Matric)", "error_ratio": {"this": null, "country": null}, "values": {"this": 29.97, "country": 29.81}, "numerators": {"this": 577704.0, "country": 7836611.0}, "error": {"this": 0, "country": 0}, "numerator_errors": {"this": 0, "country": 0}}, "Undergrad": {"index": {"this": 100.0, "country": 72.0}, "name": "Undergrad", "error_ratio": {"this": null, "country": null}, "values": {"this": 3.64, "country": 5.03}, "numerators": {"this": 70078.0, "country": 1322445.0}, "error": {"this": 0, "country": 0}, "numerator_errors": {"this": 0, "country": 0}}, "Post-grad": {"index": {"this": 100.0, "country": 60.0}, "name": "Post-grad", "error_ratio": {"this": null, "country": null}, "values": {"this": 1.71, "country": 2.87}, "numerators": {"this": 33032.0, "country": 753434.0}, "error": {"this": 0, "country": 0}, "numerator_errors": {"this": 0, "country": 0}
},
    "metadata": {
        "universe": "Invididuals 25 and over", "table_id": "HIGHESTEDUCATIONALLEVEL"
    }
}
},
    "geography": {
        "this": {
            "geo_code": "MP", "short_name": "Mpumalanga", "child_level": "municipality", "geo_level": "province", "full_name": "Mpumalanga", "full_geoid": "province-MP"
        },
        "parents": {
            "ordering": ["country"],
            "country": {
                "geo_code": "ZA", "short_name": "South Africa", "child_level": "province", "geo_level": "country", "full_name": "South Africa", "full_geoid": "country-ZA"
            }
        },
        "comparatives": ["country"]
    }
}